ndx_nirs/__init__.py
ndx_nirs/utils.py
ndx_nirs/spec/ndx-nirs.extensions.yaml
ndx_nirs/spec/ndx-nirs.namespace.yaml
tests/__init__.py
tests/integration/__init__.py
tests/integration/test_ndx_nirs.py
tests/unit/__init__.py
tests/unit/test_ndx_nirs.py
tests/unit/test_utils.py
ndx_nirs-0.3.0.dist-info/LICENSE.txt
ndx_nirs-0.3.0.dist-info/METADATA
ndx_nirs-0.3.0.dist-info/WHEEL
ndx_nirs-0.3.0.dist-info/top_level.txt
ndx_nirs-0.3.0.dist-info/RECORD
