Metadata-Version: 2.1
Name: ndx-nirs
Version: 0.3.0
Summary: An NWB extension for storing Near-Infrared Spectroscopy (NIRS) data
Home-page: https://github.com/agencyenterprise/ndx-nirs
Author: Sumner L Norman,Darin Erat Sleiter,José Ribeiro
Author-email: sumner@ae.studio,darin@ae.studio,jose@ae.studio
License: BSD 3-Clause
Classifier: Programming Language :: Python
Classifier: Programming Language :: Python :: 3.7
Classifier: Programming Language :: Python :: 3.8
Classifier: Programming Language :: Python :: 3.9
Classifier: Programming Language :: Python :: 3.10
Classifier: Intended Audience :: Developers
Classifier: Intended Audience :: Science/Research
Requires-Python: >=3.7,<3.11
License-File: LICENSE.txt
Requires-Dist: hdmf (<4,>=3.3.2)
Requires-Dist: pynwb (<3,>=2.1.0)
